polynx/__init__.py
polynx/config.py
polynx/constant.py
polynx/core.py
polynx/expr.py
polynx/expr_parser.py
polynx/frame.py
polynx/groupby.py
polynx/io.py
polynx/lazyframe.py
polynx/logging_utils.py
polynx/series.py
polynx/utils.py
polynx/wrapper.py
polynx-0.1.15.dist-info/licenses/LICENSE
polynx-0.1.15.dist-info/METADATA
polynx-0.1.15.dist-info/WHEEL
polynx-0.1.15.dist-info/top_level.txt
polynx-0.1.15.dist-info/RECORD
