Metadata-Version: 2.4
Name: polynx
Version: 0.1.15
Summary: String-powered Polars expression engine with extended DataFrame utilities
Home-page: https://github.com/LowellWinston/polynx.git
Author: Lowell Winsston
Author-email: Lowell Winston <lowell.j.winston@gmail.com>
License: MIT
Project-URL: Homepage, https://github.com/LowellWinston/polynx.git
Requires-Python: >=3.8
License-File: LICENSE
Requires-Dist: polars>=1.8
Requires-Dist: lark>=1.2.2
Requires-Dist: matplotlib>=3.7
Requires-Dist: pandas>=2.0.0
Requires-Dist: numpy>=1.24
Dynamic: author
Dynamic: home-page
Dynamic: license-file
